{
	"version": 1,
	"baseUrl": "https://github.com/86d-app/86d",
	"defaultRef": "main",
	"modules": {
		"abandoned-carts": {
			"name": "@86d-app/abandoned-carts",
			"description": "Abandoned cart tracking and recovery for 86d commerce platform",
			"version": "0.0.30",
			"category": "sales",
			"path": "modules/abandoned-carts",
			"requires": [],
			"hasStoreComponents": true,
			"hasAdminComponents": true,
			"hasStorePages": false,
			"integrity": "sha256-f5babfcb4af8718f7fb47d130259bcad011a775febbb16b28d5c932c5028f7f4"
		},
		"affiliates": {
			"name": "@86d-app/affiliates",
			"description": "Affiliate marketing program module for 86d commerce platform",
			"version": "0.0.30",
			"category": "customers",
			"path": "modules/affiliates",
			"requires": [],
			"hasStoreComponents": false,
			"hasAdminComponents": true,
			"hasStorePages": false,
			"integrity": "sha256-c5609cfd3d996e5878297878f2678cf1337e95ae218d845a2bbac6159f149484"
		},
		"amazon": {
			"name": "@86d-app/amazon",
			"description": "Amazon Marketplace integration for 86d commerce platform",
			"version": "0.0.30",
			"category": "sales",
			"path": "modules/amazon",
			"requires": [],
			"hasStoreComponents": false,
			"hasAdminComponents": true,
			"hasStorePages": false,
			"integrity": "sha256-2ea9d806795e2b5193c88dcb3f4d39454b2b2ae909de06f1df18fb8625c07e11"
		},
		"analytics": {
			"name": "@86d-app/analytics",
			"description": "Event tracking and analytics module for 86d commerce platform",
			"version": "0.0.30",
			"category": "system",
			"path": "modules/analytics",
			"requires": [],
			"hasStoreComponents": false,
			"hasAdminComponents": true,
			"hasStorePages": false,
			"integrity": "sha256-448a1c2a7879deac756cdda87fef5260f91221b6339dd9d432332a765cb88734"
		},
		"announcements": {
			"name": "@86d-app/announcements",
			"description": "Site-wide announcement bars, promotional banners, and notification banners for 86d commerce platform",
			"version": "0.0.30",
			"category": "content",
			"path": "modules/announcements",
			"requires": [],
			"hasStoreComponents": true,
			"hasAdminComponents": true,
			"hasStorePages": false,
			"integrity": "sha256-ae716abd53387d841008651c7c8c3de063e73c7b90c7bfb8d3ce990eb8c91180"
		},
		"appointments": {
			"name": "@86d-app/appointments",
			"description": "Appointments — service-based booking with staff scheduling, time slots, and customer appointment management",
			"version": "0.0.30",
			"category": "sales",
			"path": "modules/appointments",
			"requires": [
				"customers"
			],
			"hasStoreComponents": true,
			"hasAdminComponents": true,
			"hasStorePages": true,
			"integrity": "sha256-ae62a34246c7c1bb66ac7929cbf3ecdb86ce5dd1d3f4a9b9001e27607dd24973"
		},
		"auctions": {
			"name": "@86d-app/auctions",
			"description": "Time-limited product auctions with bidding, reserve prices, and buy-it-now for 86d commerce platform",
			"version": "0.0.30",
			"category": "sales",
			"path": "modules/auctions",
			"requires": [],
			"hasStoreComponents": true,
			"hasAdminComponents": true,
			"hasStorePages": true,
			"integrity": "sha256-c352545a6f7d48347fbb02ef48a9e554798ec082a65283718199ad6696c217e2"
		},
		"audit-log": {
			"name": "@86d-app/audit-log",
			"description": "Audit logging for admin actions and system events in 86d commerce platform",
			"version": "0.0.30",
			"category": "system",
			"path": "modules/audit-log",
			"requires": [],
			"hasStoreComponents": false,
			"hasAdminComponents": true,
			"hasStorePages": false,
			"integrity": "sha256-aaeb86949d62efc0c29fc88fd029919d9adebee290133f7e53ede2ece3f86fb5"
		},
		"automations": {
			"name": "@86d-app/automations",
			"description": "Event-driven workflow automation module for 86d commerce platform",
			"version": "0.0.30",
			"category": "system",
			"path": "modules/automations",
			"requires": [],
			"hasStoreComponents": false,
			"hasAdminComponents": true,
			"hasStorePages": false,
			"integrity": "sha256-f741ff73fe3efc3c558533b1482a73747bd2e31561f545d878adb241f80471e1"
		},
		"backorders": {
			"name": "@86d-app/backorders",
			"description": "Backorder management module for 86d commerce platform",
			"version": "0.0.30",
			"category": "fulfillment",
			"path": "modules/backorders",
			"requires": [
				"inventory"
			],
			"hasStoreComponents": true,
			"hasAdminComponents": true,
			"hasStorePages": false,
			"integrity": "sha256-50cfa11153fd4a4d9e3109c9a06fa28c61667561ebb40885ddcbeb22a4eab64e"
		},
		"blog": {
			"name": "@86d-app/blog",
			"description": "Blog content management module for 86d commerce platform",
			"version": "0.0.30",
			"category": "content",
			"path": "modules/blog",
			"requires": [],
			"hasStoreComponents": true,
			"hasAdminComponents": true,
			"hasStorePages": true,
			"integrity": "sha256-da49225f00ae99aeb286a09e7e0e5bf272680ef95e2e0f06758f4b9993616abe"
		},
		"braintree": {
			"name": "@86d-app/braintree",
			"description": "Braintree payment provider for 86d commerce platform",
			"version": "0.0.30",
			"category": "finance",
			"path": "modules/braintree",
			"requires": [],
			"hasStoreComponents": false,
			"hasAdminComponents": true,
			"hasStorePages": false,
			"integrity": "sha256-27dd1da9c00cf89f10d2d0267d9b17d7489d065f66151ebc38add965fde8dfaf"
		},
		"brands": {
			"name": "@86d-app/brands",
			"description": "Product brand management — organize products by manufacturer or brand with brand pages",
			"version": "0.0.30",
			"category": "catalog",
			"path": "modules/brands",
			"requires": [],
			"hasStoreComponents": true,
			"hasAdminComponents": true,
			"hasStorePages": false,
			"integrity": "sha256-d1e69e2633d574e678d861f75aae2012615aee69324c9b7e9737f06aeb6bfa6d"
		},
		"bulk-pricing": {
			"name": "@86d-app/bulk-pricing",
			"description": "Quantity-based tiered pricing — set volume discounts for products so customers pay less when buying in bulk",
			"version": "0.0.30",
			"category": "catalog",
			"path": "modules/bulk-pricing",
			"requires": [
				"products"
			],
			"hasStoreComponents": true,
			"hasAdminComponents": true,
			"hasStorePages": false,
			"integrity": "sha256-67a52609e9b9665cb499c4d316df5bb72294c7c22f3e083fc359bea18cf7b910"
		},
		"bundles": {
			"name": "@86d-app/bundles",
			"description": "Product bundles with configurable discounts for 86d commerce platform",
			"version": "0.0.30",
			"category": "catalog",
			"path": "modules/bundles",
			"requires": [],
			"hasStoreComponents": true,
			"hasAdminComponents": true,
			"hasStorePages": false,
			"integrity": "sha256-8568c24402dbda1ab900250f8a950df9d7661f2beb0249639e5603b80b9ef047"
		},
		"cart": {
			"name": "@86d-app/cart",
			"description": "Shopping cart module for 86d commerce platform",
			"version": "0.0.30",
			"category": "sales",
			"path": "modules/cart",
			"requires": [],
			"hasStoreComponents": true,
			"hasAdminComponents": true,
			"hasStorePages": false,
			"integrity": "sha256-65768f162f0ef40d1310c286ffdfd2bc4202a8919c157b1cffbc024039e3a2e9"
		},
		"checkout": {
			"name": "@86d-app/checkout",
			"description": "Checkout flow module for 86d commerce platform",
			"version": "0.0.30",
			"category": "sales",
			"path": "modules/checkout",
			"requires": [],
			"hasStoreComponents": true,
			"hasAdminComponents": true,
			"hasStorePages": false,
			"integrity": "sha256-bc4fea7d17b1a82553d5f61b30be7db5e9b61a3b925a9fa6a72b8981fd788687"
		},
		"collections": {
			"name": "@86d-app/collections",
			"description": "Curated product collections for merchandising — manual and automatic groupings",
			"version": "0.0.30",
			"category": "catalog",
			"path": "modules/collections",
			"requires": [],
			"hasStoreComponents": true,
			"hasAdminComponents": true,
			"hasStorePages": false,
			"integrity": "sha256-ba3349f5e119e80112ff931f30c2563d17a6da28646656964dabf50c2435a2f8"
		},
		"comparisons": {
			"name": "@86d-app/comparisons",
			"description": "Product comparison module for 86d commerce platform",
			"version": "0.0.30",
			"category": "marketing",
			"path": "modules/comparisons",
			"requires": [],
			"hasStoreComponents": true,
			"hasAdminComponents": true,
			"hasStorePages": false,
			"integrity": "sha256-63f11af26d8d482a4fb6de5692d5d2eb70159d5f93620143da8b4d977488b488"
		},
		"customer-groups": {
			"name": "@86d-app/customer-groups",
			"description": "Customer groups and segmentation module for 86d commerce platform",
			"version": "0.0.30",
			"category": "customers",
			"path": "modules/customer-groups",
			"requires": [],
			"hasStoreComponents": false,
			"hasAdminComponents": true,
			"hasStorePages": false,
			"integrity": "sha256-a5cfc874aa5295b6c4bba72ecbd67c4013ce84b1b57b4744f106c226dafe4c51"
		},
		"customers": {
			"name": "@86d-app/customers",
			"description": "Customer management module for 86d commerce platform",
			"version": "0.0.30",
			"category": "customers",
			"path": "modules/customers",
			"requires": [],
			"hasStoreComponents": true,
			"hasAdminComponents": true,
			"hasStorePages": false,
			"integrity": "sha256-c5ad4562262c44b52192d7bfceb1633b75d63347e8c6b1dd6e98ba3165636837"
		},
		"delivery-slots": {
			"name": "@86d-app/delivery-slots",
			"description": "Delivery slots — define delivery time windows by day of week with capacity limits, surcharges, and blackout dates",
			"version": "0.0.30",
			"category": "fulfillment",
			"path": "modules/delivery-slots",
			"requires": [
				"orders"
			],
			"hasStoreComponents": true,
			"hasAdminComponents": true,
			"hasStorePages": true,
			"integrity": "sha256-38848c4989c3b9027764ac61fafef84a7e67c33b2a0065fd885f3c7f0c52eba4"
		},
		"digital-downloads": {
			"name": "@86d-app/digital-downloads",
			"description": "Digital file delivery module for 86d commerce platform",
			"version": "0.0.30",
			"category": "sales",
			"path": "modules/digital-downloads",
			"requires": [],
			"hasStoreComponents": true,
			"hasAdminComponents": true,
			"hasStorePages": true,
			"integrity": "sha256-0eaea5806143683b7c0707963c592f77a713f7c5a581f2b1447025cbc1bdce18"
		},
		"discounts": {
			"name": "@86d-app/discounts",
			"description": "Discount codes and promotions module for 86d commerce platform",
			"version": "0.0.30",
			"category": "marketing",
			"path": "modules/discounts",
			"requires": [],
			"hasStoreComponents": true,
			"hasAdminComponents": true,
			"hasStorePages": false,
			"integrity": "sha256-4adc1b11b906707029fb6c0c714351ffad1ed8b1b44c988591c1a39eed9b624d"
		},
		"doordash": {
			"name": "@86d-app/doordash",
			"description": "DoorDash Drive delivery integration module for 86d commerce platform",
			"version": "0.0.30",
			"category": "fulfillment",
			"path": "modules/doordash",
			"requires": [],
			"hasStoreComponents": true,
			"hasAdminComponents": true,
			"hasStorePages": false,
			"integrity": "sha256-6e1b3630379d81d11e8e28dade7b0c29334ac10c2129626f0c2a5d0862e9cfc9"
		},
		"ebay": {
			"name": "@86d-app/ebay",
			"description": "eBay marketplace integration for 86d commerce platform",
			"version": "0.0.30",
			"category": "sales",
			"path": "modules/ebay",
			"requires": [],
			"hasStoreComponents": true,
			"hasAdminComponents": true,
			"hasStorePages": false,
			"integrity": "sha256-bb091ea7cecc99d2ad72d0fbf8233369a6e92ef4f21ba190b6c6d83a9f84da3e"
		},
		"etsy": {
			"name": "@86d-app/etsy",
			"description": "Etsy Marketplace integration for 86d commerce platform",
			"version": "0.0.30",
			"category": "sales",
			"path": "modules/etsy",
			"requires": [],
			"hasStoreComponents": false,
			"hasAdminComponents": true,
			"hasStorePages": false,
			"integrity": "sha256-b06bb44c97f9625f67affa43f461c4af70080330a4f85c84215ae0793cdf665f"
		},
		"facebook-shop": {
			"name": "@86d-app/facebook-shop",
			"description": "Facebook/Meta Commerce sales channel module for 86d commerce platform",
			"version": "0.0.30",
			"category": "sales",
			"path": "modules/facebook-shop",
			"requires": [],
			"hasStoreComponents": false,
			"hasAdminComponents": true,
			"hasStorePages": false,
			"integrity": "sha256-0ca40df27e1c145c4ffcab533579eb89594aa5275057dda633f15323d62a4210"
		},
		"faq": {
			"name": "@86d-app/faq",
			"description": "FAQ and knowledge base module for 86d commerce platform",
			"version": "0.0.30",
			"category": "content",
			"path": "modules/faq",
			"requires": [],
			"hasStoreComponents": true,
			"hasAdminComponents": true,
			"hasStorePages": false,
			"integrity": "sha256-6b8c241a1f99b80987ee4fcecaa4d77e1d9e93f25466905305dd24039de594c8"
		},
		"favor": {
			"name": "@86d-app/favor",
			"description": "Favor delivery service integration for 86d commerce platform",
			"version": "0.0.30",
			"category": "fulfillment",
			"path": "modules/favor",
			"requires": [],
			"hasStoreComponents": true,
			"hasAdminComponents": true,
			"hasStorePages": false,
			"integrity": "sha256-014c4271d21f68bdc9f449f79d4784a0a62d4a4c6804bd8014a637dc48c9d720"
		},
		"flash-sales": {
			"name": "@86d-app/flash-sales",
			"description": "Flash sales — time-limited promotional events with countdown timers, per-product sale pricing, and stock limits",
			"version": "0.0.30",
			"category": "sales",
			"path": "modules/flash-sales",
			"requires": [
				"products"
			],
			"hasStoreComponents": true,
			"hasAdminComponents": true,
			"hasStorePages": true,
			"integrity": "sha256-d3ea02d9e3d26079151a62a79f77c9790372e292a5a9562262cd6d3a94d6663b"
		},
		"forms": {
			"name": "@86d-app/forms",
			"description": "Custom forms module for 86d commerce platform — contact forms, surveys, inquiries",
			"version": "0.0.30",
			"category": "content",
			"path": "modules/forms",
			"requires": [],
			"hasStoreComponents": true,
			"hasAdminComponents": true,
			"hasStorePages": false,
			"integrity": "sha256-749a96ea21299f76f4ad0b10ba2f56c61ab8a7a6d22124734279d53dc3f6ef21"
		},
		"fulfillment": {
			"name": "@86d-app/fulfillment",
			"description": "Order fulfillment management for 86d commerce platform",
			"version": "0.0.30",
			"category": "fulfillment",
			"path": "modules/fulfillment",
			"requires": [],
			"hasStoreComponents": true,
			"hasAdminComponents": true,
			"hasStorePages": false,
			"integrity": "sha256-4bf8576f633696983fa5851f4aa88a08b4c06183476900575d9d716e1ae1e36c"
		},
		"gamification": {
			"name": "@86d-app/gamification",
			"description": "Gamified promotions module for 86d commerce platform — spin the wheel, scratch cards, slot machine",
			"version": "0.0.30",
			"category": "marketing",
			"path": "modules/gamification",
			"requires": [],
			"hasStoreComponents": false,
			"hasAdminComponents": true,
			"hasStorePages": false,
			"integrity": "sha256-02e41ddebf5f150db25aa9f18b82597800899da46f1733dc52473c81c1118730"
		},
		"gift-registry": {
			"name": "@86d-app/gift-registry",
			"description": "",
			"version": "0.0.30",
			"category": "sales",
			"path": "modules/gift-registry",
			"requires": [],
			"hasStoreComponents": true,
			"hasAdminComponents": true,
			"hasStorePages": true,
			"integrity": "sha256-31e3193ffa954083959e7aa790722f750472f4ab542dbbf637858cb816b7744e"
		},
		"gift-wrapping": {
			"name": "@86d-app/gift-wrapping",
			"description": "Gift wrapping — add-on wrapping options for order items with custom messages and recipient names",
			"version": "0.0.30",
			"category": "sales",
			"path": "modules/gift-wrapping",
			"requires": [
				"orders"
			],
			"hasStoreComponents": true,
			"hasAdminComponents": true,
			"hasStorePages": true,
			"integrity": "sha256-c549621a5ba59b22a8376930e91badabefa6d63c21f419c3f619465086e55f76"
		},
		"giftcards": {
			"name": "@86d-app/giftcards",
			"description": "Gift card issuance, balance management, and payment integration for 86d commerce platform",
			"version": "0.0.30",
			"category": "sales",
			"path": "modules/giftcards",
			"requires": [],
			"hasStoreComponents": true,
			"hasAdminComponents": true,
			"hasStorePages": false,
			"integrity": "sha256-0c9a009d28f8db36d7574b9daa3ed4db39f2a37981afba688667b16432b4c999"
		},
		"google-shopping": {
			"name": "@86d-app/google-shopping",
			"description": "Google Shopping / Merchant Center integration for 86d commerce platform",
			"version": "0.0.30",
			"category": "sales",
			"path": "modules/google-shopping",
			"requires": [],
			"hasStoreComponents": false,
			"hasAdminComponents": true,
			"hasStorePages": false,
			"integrity": "sha256-cc921b9ef29337d4dd941c8e260b3180cf8a7a19e82322429ca15fbcccf55158"
		},
		"import-export": {
			"name": "@86d-app/import-export",
			"description": "Bulk import and export for products, orders, customers, and inventory in 86d commerce platform",
			"version": "0.0.30",
			"category": "system",
			"path": "modules/import-export",
			"requires": [],
			"hasStoreComponents": false,
			"hasAdminComponents": true,
			"hasStorePages": false,
			"integrity": "sha256-ef8857e77cf26e5f2481065c3fd16e053c88296309952cc5f07275aa3a4a57c1"
		},
		"instagram-shop": {
			"name": "@86d-app/instagram-shop",
			"description": "Instagram Shopping sales channel module for 86d commerce platform",
			"version": "0.0.30",
			"category": "sales",
			"path": "modules/instagram-shop",
			"requires": [],
			"hasStoreComponents": false,
			"hasAdminComponents": true,
			"hasStorePages": false,
			"integrity": "sha256-8a66e99847c161b02be082e852ba00b5818e50ab97bc4721875cb8021ec9d98d"
		},
		"inventory": {
			"name": "@86d-app/inventory",
			"description": "Inventory and stock tracking module for 86d commerce platform",
			"version": "0.0.30",
			"category": "fulfillment",
			"path": "modules/inventory",
			"requires": [],
			"hasStoreComponents": true,
			"hasAdminComponents": true,
			"hasStorePages": false,
			"integrity": "sha256-75977e8aba21f82b56b2f781466e243d0697fbc570e4be7149b3bc70c0ec46a5"
		},
		"invoices": {
			"name": "@86d-app/invoices",
			"description": "Invoices — invoice lifecycle management with payment terms, partial payments, credit notes, and configurable numbering",
			"version": "0.0.30",
			"category": "sales",
			"path": "modules/invoices",
			"requires": [
				"orders"
			],
			"hasStoreComponents": true,
			"hasAdminComponents": true,
			"hasStorePages": false,
			"integrity": "sha256-cafdb89d4d5299afdb94cfff1c5e847e19bb98444470ef584bd2c052b6c2de0d"
		},
		"kiosk": {
			"name": "@86d-app/kiosk",
			"description": "Self-service ordering kiosk module for 86d commerce platform",
			"version": "0.0.30",
			"category": "sales",
			"path": "modules/kiosk",
			"requires": [],
			"hasStoreComponents": true,
			"hasAdminComponents": true,
			"hasStorePages": false,
			"integrity": "sha256-d0c1af23eff8c0480e118be7424e444d73ae33e5282d319cd4143655fa6de580"
		},
		"loyalty": {
			"name": "@86d-app/loyalty",
			"description": "Customer loyalty and rewards points module for 86d commerce platform",
			"version": "0.0.30",
			"category": "customers",
			"path": "modules/loyalty",
			"requires": [
				"customers"
			],
			"hasStoreComponents": true,
			"hasAdminComponents": true,
			"hasStorePages": true,
			"integrity": "sha256-48c5895b5af42eb8463b8553290b42d3805be9ee6c4e0ff45dffb6da0831e390"
		},
		"media": {
			"name": "@86d-app/media",
			"description": "Media and asset management module for 86d commerce platform",
			"version": "0.0.30",
			"category": "content",
			"path": "modules/media",
			"requires": [],
			"hasStoreComponents": true,
			"hasAdminComponents": true,
			"hasStorePages": false,
			"integrity": "sha256-4584902358e4bfdc51d1499f5019e382dcea7e62f789fb6585b9ec259cd8567e"
		},
		"memberships": {
			"name": "@86d-app/memberships",
			"description": "Paid membership plans — recurring subscriptions with exclusive benefits, gated products, and member pricing",
			"version": "0.0.30",
			"category": "customers",
			"path": "modules/memberships",
			"requires": [
				"customers"
			],
			"hasStoreComponents": true,
			"hasAdminComponents": true,
			"hasStorePages": true,
			"integrity": "sha256-0df5aff5d8cfe3e8b7393a49208e667096faa36764801cc660eb5a46399d1251"
		},
		"multi-currency": {
			"name": "@86d-app/multi-currency",
			"description": "Multi-currency support module for 86d commerce platform",
			"version": "0.0.30",
			"category": "finance",
			"path": "modules/multi-currency",
			"requires": [],
			"hasStoreComponents": true,
			"hasAdminComponents": true,
			"hasStorePages": false,
			"integrity": "sha256-27fd4c3896160a279c2a86c59131b3fd459698ec8ffeddbb44805ef7bf146f42"
		},
		"navigation": {
			"name": "@86d-app/navigation",
			"description": "Store navigation and menu management module for 86d commerce platform",
			"version": "0.0.30",
			"category": "content",
			"path": "modules/navigation",
			"requires": [],
			"hasStoreComponents": true,
			"hasAdminComponents": true,
			"hasStorePages": false,
			"integrity": "sha256-491352ac1281150e081f3ad25abbd2339734ab7b64f62647d85c715c83f32bf0"
		},
		"newsletter": {
			"name": "@86d-app/newsletter",
			"description": "Newsletter subscription management module for 86d commerce platform",
			"version": "0.0.30",
			"category": "marketing",
			"path": "modules/newsletter",
			"requires": [],
			"hasStoreComponents": true,
			"hasAdminComponents": true,
			"hasStorePages": false,
			"integrity": "sha256-5f7e65144c21fe971d7c3ffabd42eb2d7f1865e699e1f8d1ea4855b2cf84b930"
		},
		"notifications": {
			"name": "@86d-app/notifications",
			"description": "In-app notification management module for 86d commerce platform",
			"version": "0.0.30",
			"category": "support",
			"path": "modules/notifications",
			"requires": [],
			"hasStoreComponents": true,
			"hasAdminComponents": true,
			"hasStorePages": false,
			"integrity": "sha256-02482c5aa2c54ac51d44c4102b26f207fabc2d183650a6b0938611ccc0c50c16"
		},
		"order-notes": {
			"name": "@86d-app/order-notes",
			"description": "Order notes and comments module for 86d commerce platform",
			"version": "0.0.30",
			"category": "sales",
			"path": "modules/order-notes",
			"requires": [],
			"hasStoreComponents": true,
			"hasAdminComponents": true,
			"hasStorePages": false,
			"integrity": "sha256-449453d9fa95da69b879fd1dd4e505fbc1c131ba74bac11904dade3ac6cc934d"
		},
		"orders": {
			"name": "@86d-app/orders",
			"description": "Order management module for 86d commerce platform",
			"version": "0.0.30",
			"category": "sales",
			"path": "modules/orders",
			"requires": [],
			"hasStoreComponents": true,
			"hasAdminComponents": true,
			"hasStorePages": false,
			"integrity": "sha256-1a6611f0868c6b8380330a138fb086c64777756bec446177c6415e4ab8f50e05"
		},
		"pages": {
			"name": "@86d-app/pages",
			"description": "Custom content pages module for 86d commerce platform",
			"version": "0.0.30",
			"category": "content",
			"path": "modules/pages",
			"requires": [],
			"hasStoreComponents": true,
			"hasAdminComponents": true,
			"hasStorePages": true,
			"integrity": "sha256-21a3af1cc5188be2cea175f3f68cb8e903f9219fb843b841b7ed24957d22443b"
		},
		"payments": {
			"name": "@86d-app/payments",
			"description": "Payment processing abstraction for 86d commerce platform",
			"version": "0.0.30",
			"category": "sales",
			"path": "modules/payments",
			"requires": [],
			"hasStoreComponents": false,
			"hasAdminComponents": true,
			"hasStorePages": false,
			"integrity": "sha256-d66fc69868b29cd340a5de022da6e350e7b53c9d2523c25aa0d70892eb43794b"
		},
		"paypal": {
			"name": "@86d-app/paypal",
			"description": "PayPal payment provider for 86d commerce platform",
			"version": "0.0.30",
			"category": "finance",
			"path": "modules/paypal",
			"requires": [],
			"hasStoreComponents": false,
			"hasAdminComponents": true,
			"hasStorePages": false,
			"integrity": "sha256-2b26d9591c1ae779696ad078c345990d0fdc2a8ff1459d250d0397cb774a3e53"
		},
		"photo-booth": {
			"name": "@86d-app/photo-booth",
			"description": "Photo booth module for 86d commerce platform — capture, stream, and share photos at events",
			"version": "0.0.30",
			"category": "marketing",
			"path": "modules/photo-booth",
			"requires": [],
			"hasStoreComponents": false,
			"hasAdminComponents": true,
			"hasStorePages": false,
			"integrity": "sha256-074878a210918677a1aec18df8fd2bf2699a43f32ecf9117aab9203b30c68e74"
		},
		"pinterest-shop": {
			"name": "@86d-app/pinterest-shop",
			"description": "Pinterest shopping integration for 86d commerce platform",
			"version": "0.0.30",
			"category": "sales",
			"path": "modules/pinterest-shop",
			"requires": [],
			"hasStoreComponents": true,
			"hasAdminComponents": true,
			"hasStorePages": false,
			"integrity": "sha256-0fbde85fe850884664716f456e54e052db4a8b6c8a419643ec62a665c601349d"
		},
		"preorders": {
			"name": "@86d-app/preorders",
			"description": "Preorder campaign management module for 86d commerce platform",
			"version": "0.0.30",
			"category": "fulfillment",
			"path": "modules/preorders",
			"requires": [
				"products"
			],
			"hasStoreComponents": true,
			"hasAdminComponents": true,
			"hasStorePages": false,
			"integrity": "sha256-763b7b3c13ad0e1aee8d1bc2f938e2afbbf3ceb15d8806e1d865a1828dd3f41e"
		},
		"price-lists": {
			"name": "@86d-app/price-lists",
			"description": "Price list management — B2B/wholesale pricing, volume tiers, customer-group-specific pricing, and scheduled price overrides",
			"version": "0.0.30",
			"category": "catalog",
			"path": "modules/price-lists",
			"requires": [
				"products"
			],
			"hasStoreComponents": false,
			"hasAdminComponents": true,
			"hasStorePages": false,
			"integrity": "sha256-d049e265de797a38ac9332b0cf879dbc3c6e2302e69c8296b5bfa876c043b30a"
		},
		"product-feeds": {
			"name": "@86d-app/product-feeds",
			"description": "Product feed generation for Google Shopping, Facebook/Meta catalog, and custom channels in 86d commerce platform",
			"version": "0.0.30",
			"category": "marketing",
			"path": "modules/product-feeds",
			"requires": [],
			"hasStoreComponents": false,
			"hasAdminComponents": true,
			"hasStorePages": false,
			"integrity": "sha256-22d6e5604d17b8c02af269fa37d175eb3b6bd3bcbaf7431df94a0910436b8aca"
		},
		"product-labels": {
			"name": "@86d-app/product-labels",
			"description": "Product labels and badges module for 86d commerce platform",
			"version": "0.0.30",
			"category": "catalog",
			"path": "modules/product-labels",
			"requires": [],
			"hasStoreComponents": true,
			"hasAdminComponents": true,
			"hasStorePages": false,
			"integrity": "sha256-61144cb64a891feb8de75c01ae821ca776d06d69527d54faf0777d7f41e4f14a"
		},
		"product-qa": {
			"name": "@86d-app/product-qa",
			"description": "Product questions and answers module for 86d commerce platform",
			"version": "0.0.30",
			"category": "marketing",
			"path": "modules/product-qa",
			"requires": [],
			"hasStoreComponents": true,
			"hasAdminComponents": true,
			"hasStorePages": false,
			"integrity": "sha256-769eff9e5799dcc85a6ae414583d858896e718e011e15eaf4943f74d02bcbe77"
		},
		"products": {
			"name": "@86d-app/products",
			"description": "Product catalog module for 86d commerce platform",
			"version": "0.0.30",
			"category": "catalog",
			"path": "modules/products",
			"requires": [],
			"hasStoreComponents": true,
			"hasAdminComponents": true,
			"hasStorePages": true,
			"integrity": "sha256-a4eba9b8e0abd6b9e7aec2537fa41b57b986bcb1e4ba68d17ff11322cbbf9275"
		},
		"qr-code": {
			"name": "@86d-app/qr-code",
			"description": "QR code generation and management module for 86d commerce platform",
			"version": "0.0.30",
			"category": "marketing",
			"path": "modules/qr-code",
			"requires": [],
			"hasStoreComponents": false,
			"hasAdminComponents": true,
			"hasStorePages": false,
			"integrity": "sha256-35ed58e2b264177db5bc47d84861af41e09e4ec6a3f534482d714226f0fa982b"
		},
		"quotes": {
			"name": "@86d-app/quotes",
			"description": "",
			"version": "0.0.30",
			"category": "sales",
			"path": "modules/quotes",
			"requires": [],
			"hasStoreComponents": true,
			"hasAdminComponents": true,
			"hasStorePages": true,
			"integrity": "sha256-c32908189ea326b41b4a3665060239ef8e34157350053da3c3e120fe0610587e"
		},
		"recently-viewed": {
			"name": "@86d-app/recently-viewed",
			"description": "Recently viewed products tracking module for 86d commerce platform",
			"version": "0.0.30",
			"category": "marketing",
			"path": "modules/recently-viewed",
			"requires": [],
			"hasStoreComponents": true,
			"hasAdminComponents": true,
			"hasStorePages": false,
			"integrity": "sha256-ea0129fd7129b5758aa6ae7d21d72b2dfcbd635c30487fbb29ba490730def4b4"
		},
		"recommendations": {
			"name": "@86d-app/recommendations",
			"description": "Product recommendation engine for 86d commerce platform",
			"version": "0.0.30",
			"category": "marketing",
			"path": "modules/recommendations",
			"requires": [],
			"hasStoreComponents": true,
			"hasAdminComponents": true,
			"hasStorePages": false,
			"integrity": "sha256-803bccc8895ecee08e0a0c908bdaef1d66d6fa1806c6942b27bd47195719ab9d"
		},
		"redirects": {
			"name": "@86d-app/redirects",
			"description": "URL redirect management — 301/302/307/308 redirects for SEO and URL migration",
			"version": "0.0.30",
			"category": "content",
			"path": "modules/redirects",
			"requires": [],
			"hasStoreComponents": false,
			"hasAdminComponents": true,
			"hasStorePages": false,
			"integrity": "sha256-fe003d59af2b14f66ee4eca0fa25c7a4a098de91bb7764c0d93d952afedda445"
		},
		"referrals": {
			"name": "@86d-app/referrals",
			"description": "Customer referral program module for 86d commerce platform",
			"version": "0.0.30",
			"category": "customers",
			"path": "modules/referrals",
			"requires": [],
			"hasStoreComponents": true,
			"hasAdminComponents": true,
			"hasStorePages": true,
			"integrity": "sha256-581e8eab820d3af763fbc95d5d030131cc2204111ed7898fd8caa8cc339578f2"
		},
		"returns": {
			"name": "@86d-app/returns",
			"description": "Return request management for 86d commerce platform",
			"version": "0.0.30",
			"category": "sales",
			"path": "modules/returns",
			"requires": [],
			"hasStoreComponents": true,
			"hasAdminComponents": true,
			"hasStorePages": false,
			"integrity": "sha256-0b5210a8fb3c9028d9c546fd0446e260f50b3db56ed371b58486fbf4a5e29281"
		},
		"reviews": {
			"name": "@86d-app/reviews",
			"description": "Product reviews and ratings module for 86d commerce platform",
			"version": "0.0.30",
			"category": "marketing",
			"path": "modules/reviews",
			"requires": [],
			"hasStoreComponents": true,
			"hasAdminComponents": true,
			"hasStorePages": false,
			"integrity": "sha256-00f7ccc2bcab4cdc6745fcb650f830d3ed70c72b2956fbdb9db816b9fc981599"
		},
		"saved-addresses": {
			"name": "@86d-app/saved-addresses",
			"description": "Customer address book module for 86d commerce platform",
			"version": "0.0.30",
			"category": "customers",
			"path": "modules/saved-addresses",
			"requires": [],
			"hasStoreComponents": true,
			"hasAdminComponents": true,
			"hasStorePages": false,
			"integrity": "sha256-6fc41e0cd475ade72ffa81df19cc25ae41b4977063be4dbd389ac117adc08f97"
		},
		"search": {
			"name": "@86d-app/search",
			"description": "Unified search, autocomplete, and search analytics module for 86d commerce platform",
			"version": "0.0.30",
			"category": "system",
			"path": "modules/search",
			"requires": [],
			"hasStoreComponents": true,
			"hasAdminComponents": true,
			"hasStorePages": true,
			"integrity": "sha256-920908f98ddf2f5a60edff5808a30e238cf3cc75e7430467331c1212c08410cf"
		},
		"seo": {
			"name": "@86d-app/seo",
			"description": "SEO management module for 86d commerce platform — meta tags, redirects, and sitemaps",
			"version": "0.0.30",
			"category": "content",
			"path": "modules/seo",
			"requires": [],
			"hasStoreComponents": true,
			"hasAdminComponents": true,
			"hasStorePages": true,
			"integrity": "sha256-9e291aab04923e2890de9e6463f91e2f81d8b0f7886614213ef319456dc286ca"
		},
		"settings": {
			"name": "@86d-app/settings",
			"description": "Store settings and configuration module for 86d commerce platform",
			"version": "0.0.30",
			"category": "system",
			"path": "modules/settings",
			"requires": [],
			"hasStoreComponents": false,
			"hasAdminComponents": true,
			"hasStorePages": false,
			"integrity": "sha256-8bdaa04a7f1015a4a6871958a59a8535bac6f8b72da15c52f9e9588ae4b34e7a"
		},
		"shipping": {
			"name": "@86d-app/shipping",
			"description": "Shipping zones and rates module for 86d commerce platform",
			"version": "0.0.30",
			"category": "fulfillment",
			"path": "modules/shipping",
			"requires": [],
			"hasStoreComponents": true,
			"hasAdminComponents": true,
			"hasStorePages": false,
			"integrity": "sha256-40b765ea6bbecaa5c3304265a358313327588ba679e6723a271b17ae9ca02e82"
		},
		"sitemap": {
			"name": "@86d-app/sitemap",
			"description": "XML sitemap generation — auto-generate sitemaps from products, collections, pages, and blog posts",
			"version": "0.0.30",
			"category": "content",
			"path": "modules/sitemap",
			"requires": [],
			"hasStoreComponents": false,
			"hasAdminComponents": true,
			"hasStorePages": false,
			"integrity": "sha256-54fa2a297848d152fc606b81e1cde2afce392b92c0fb8b611923a27e0387bb87"
		},
		"social-proof": {
			"name": "@86d-app/social-proof",
			"description": "Social proof and trust signals module for 86d commerce platform",
			"version": "0.0.30",
			"category": "marketing",
			"path": "modules/social-proof",
			"requires": [],
			"hasStoreComponents": true,
			"hasAdminComponents": true,
			"hasStorePages": false,
			"integrity": "sha256-b0dd2eade6362d0f4f86e3d44052027cd73c9e2ebf9e1030761764a1f2161311"
		},
		"social-sharing": {
			"name": "@86d-app/social-sharing",
			"description": "Social sharing and share tracking module for 86d commerce platform",
			"version": "0.0.30",
			"category": "marketing",
			"path": "modules/social-sharing",
			"requires": [],
			"hasStoreComponents": true,
			"hasAdminComponents": true,
			"hasStorePages": false,
			"integrity": "sha256-10873bd4fe4acf9b5cc3162b2d517b38b59026dfefd7957b257a0c3becada334"
		},
		"square": {
			"name": "@86d-app/square",
			"description": "Square payment provider for 86d commerce platform",
			"version": "0.0.30",
			"category": "finance",
			"path": "modules/square",
			"requires": [],
			"hasStoreComponents": false,
			"hasAdminComponents": true,
			"hasStorePages": false,
			"integrity": "sha256-af9ebdee3cb8ba41f14581e71e47b8aa877f00f95e588fd7243ef735f75d30e0"
		},
		"store-credits": {
			"name": "@86d-app/store-credits",
			"description": "Store credit accounts and transactions for 86d commerce platform",
			"version": "0.0.30",
			"category": "customers",
			"path": "modules/store-credits",
			"requires": [],
			"hasStoreComponents": true,
			"hasAdminComponents": true,
			"hasStorePages": false,
			"integrity": "sha256-37f62224bcbda7e02bc415fd9e3f3fbabf62d5a006239a32fd86b98824a7cd1c"
		},
		"store-locator": {
			"name": "@86d-app/store-locator",
			"description": "Physical store location management and proximity search for 86d commerce platform",
			"version": "0.0.30",
			"category": "content",
			"path": "modules/store-locator",
			"requires": [],
			"hasStoreComponents": true,
			"hasAdminComponents": true,
			"hasStorePages": false,
			"integrity": "sha256-eab9642909353560eff1d16c49b4bcb835fe5460c1027caa820c198985d9e85f"
		},
		"store-pickup": {
			"name": "@86d-app/store-pickup",
			"description": "Store pickup (BOPIS) — let customers buy online and pick up in store with location management and time windows",
			"version": "0.0.30",
			"category": "fulfillment",
			"path": "modules/store-pickup",
			"requires": [
				"orders"
			],
			"hasStoreComponents": true,
			"hasAdminComponents": true,
			"hasStorePages": true,
			"integrity": "sha256-93a67988d6c84a238439f56fdfc8cbe06c52490d43b81b3742a6dffa7fd6bcc4"
		},
		"stripe": {
			"name": "@86d-app/stripe",
			"description": "Stripe payment provider for 86d commerce platform",
			"version": "0.0.30",
			"category": "finance",
			"path": "modules/stripe",
			"requires": [],
			"hasStoreComponents": false,
			"hasAdminComponents": true,
			"hasStorePages": false,
			"integrity": "sha256-14cb46a001dbbc4d52802a47131dedc4a97d9c91e8fa39b0bb3cd993e4b25ca6"
		},
		"subscriptions": {
			"name": "@86d-app/subscriptions",
			"description": "Subscription plans and recurring billing module for 86d commerce platform",
			"version": "0.0.30",
			"category": "sales",
			"path": "modules/subscriptions",
			"requires": [],
			"hasStoreComponents": true,
			"hasAdminComponents": true,
			"hasStorePages": false,
			"integrity": "sha256-f7529594a472a048ceec60241b0c7fe769a3fccc514e967945d6b058d9acb672"
		},
		"tax": {
			"name": "@86d-app/tax",
			"description": "Tax calculation and management module for 86d commerce platform",
			"version": "0.0.30",
			"category": "finance",
			"path": "modules/tax",
			"requires": [],
			"hasStoreComponents": true,
			"hasAdminComponents": true,
			"hasStorePages": false,
			"integrity": "sha256-020ee7f57477ea9486878cec3053fad28c22a99eea9165e991da22cae5de4e4f"
		},
		"tickets": {
			"name": "@86d-app/tickets",
			"description": "Customer support tickets module for 86d commerce platform",
			"version": "0.0.30",
			"category": "support",
			"path": "modules/tickets",
			"requires": [],
			"hasStoreComponents": true,
			"hasAdminComponents": true,
			"hasStorePages": true,
			"integrity": "sha256-e67b8fa2d61cdb059fee132e707e0b2115d66ff7ab35d6f70d7d41303fb08d52"
		},
		"tiktok-shop": {
			"name": "@86d-app/tiktok-shop",
			"description": "TikTok Shop sales channel module for 86d commerce platform",
			"version": "0.0.30",
			"category": "sales",
			"path": "modules/tiktok-shop",
			"requires": [],
			"hasStoreComponents": false,
			"hasAdminComponents": true,
			"hasStorePages": false,
			"integrity": "sha256-222054ce55057250b5f78b94d6e155fc5ff1ea95067482c158ccfc3cabed554b"
		},
		"tipping": {
			"name": "@86d-app/tipping",
			"description": "Configurable tipping system for orders, delivery, and services on 86d commerce platform",
			"version": "0.0.30",
			"category": "sales",
			"path": "modules/tipping",
			"requires": [],
			"hasStoreComponents": true,
			"hasAdminComponents": true,
			"hasStorePages": false,
			"integrity": "sha256-cb5b842f0af36d9f3847229e0742daeb28f56de78a3319d8cefa8cf1d4d5d10f"
		},
		"toast": {
			"name": "@86d-app/toast",
			"description": "Toast POS integration module for 86d commerce platform",
			"version": "0.0.30",
			"category": "sales",
			"path": "modules/toast",
			"requires": [],
			"hasStoreComponents": true,
			"hasAdminComponents": true,
			"hasStorePages": false,
			"integrity": "sha256-9047f60d6285e30611a67d29ff88b048966575bf1d66055d2eac9b989e97645c"
		},
		"uber-direct": {
			"name": "@86d-app/uber-direct",
			"description": "Uber Direct on-demand delivery integration for 86d commerce platform",
			"version": "0.0.30",
			"category": "fulfillment",
			"path": "modules/uber-direct",
			"requires": [],
			"hasStoreComponents": true,
			"hasAdminComponents": true,
			"hasStorePages": false,
			"integrity": "sha256-5933b3a24336e3eda081f97a7f5e29d87fbf2d4821cfe5336cb42978e5d6c1c2"
		},
		"uber-eats": {
			"name": "@86d-app/uber-eats",
			"description": "Uber Eats marketplace integration module for 86d commerce platform",
			"version": "0.0.30",
			"category": "sales",
			"path": "modules/uber-eats",
			"requires": [],
			"hasStoreComponents": true,
			"hasAdminComponents": true,
			"hasStorePages": false,
			"integrity": "sha256-1a21fa781a633f60e72c0d59ddb0f5b150bb44840f1f770f71b949db7942877d"
		},
		"vendors": {
			"name": "@86d-app/vendors",
			"description": "Multi-vendor marketplace — vendor profiles, product assignments, commission tracking, and payout management",
			"version": "0.0.30",
			"category": "catalog",
			"path": "modules/vendors",
			"requires": [
				"products"
			],
			"hasStoreComponents": false,
			"hasAdminComponents": true,
			"hasStorePages": false,
			"integrity": "sha256-73e3b9ce7bda4c74f615d890baa92e16dceb29f6c6f2f76df82cc6ebda24dd02"
		},
		"waitlist": {
			"name": "@86d-app/waitlist",
			"description": "Back-in-stock waitlist and notification module for 86d commerce platform",
			"version": "0.0.30",
			"category": "marketing",
			"path": "modules/waitlist",
			"requires": [
				"inventory"
			],
			"hasStoreComponents": true,
			"hasAdminComponents": true,
			"hasStorePages": false,
			"integrity": "sha256-c65ea54301e82dd45031f779cbc4ae8c5a964ac5b6971d0f07800aff140619f1"
		},
		"walmart": {
			"name": "@86d-app/walmart",
			"description": "Walmart marketplace integration for 86d commerce platform",
			"version": "0.0.30",
			"category": "sales",
			"path": "modules/walmart",
			"requires": [],
			"hasStoreComponents": true,
			"hasAdminComponents": true,
			"hasStorePages": false,
			"integrity": "sha256-565b870ee3b2f83febfdbba84606263c63aeb8a5783d142d0ca77c849864a025"
		},
		"warranties": {
			"name": "@86d-app/warranties",
			"description": "Product warranty plans, registrations, and claims for 86d commerce platform",
			"version": "0.0.30",
			"category": "sales",
			"path": "modules/warranties",
			"requires": [],
			"hasStoreComponents": true,
			"hasAdminComponents": true,
			"hasStorePages": false,
			"integrity": "sha256-5a1c621785dd0992946f08d4d8050bee83de676fb6050378053e99fb93c5826e"
		},
		"wish": {
			"name": "@86d-app/wish",
			"description": "Wish marketplace integration for 86d commerce platform",
			"version": "0.0.30",
			"category": "sales",
			"path": "modules/wish",
			"requires": [],
			"hasStoreComponents": true,
			"hasAdminComponents": true,
			"hasStorePages": false,
			"integrity": "sha256-e1e2bc5baab9a28d56d150bbc72ba6aec022165ae37c0954a0cd46191c808494"
		},
		"wishlist": {
			"name": "@86d-app/wishlist",
			"description": "Customer wishlist and favorites module for 86d commerce platform",
			"version": "0.0.30",
			"category": "marketing",
			"path": "modules/wishlist",
			"requires": [],
			"hasStoreComponents": true,
			"hasAdminComponents": true,
			"hasStorePages": false,
			"integrity": "sha256-8a56b46aa5bf701c02a91ff692c52f1b5e620add0643eeaca0d17a3111cd7bc9"
		},
		"x-shop": {
			"name": "@86d-app/x-shop",
			"description": "X/Twitter Shopping sales channel module for 86d commerce platform",
			"version": "0.0.30",
			"category": "sales",
			"path": "modules/x-shop",
			"requires": [],
			"hasStoreComponents": true,
			"hasAdminComponents": true,
			"hasStorePages": false,
			"integrity": "sha256-2504f4a74bf061947bc2bd6d6999c808b67c517dbe1230bf6860f449fd01e5b0"
		}
	},
	"templates": {
		"brisa": {
			"name": "brisa",
			"description": "86d Starter Kit",
			"version": "0.0.1",
			"path": "templates/brisa"
		}
	}
}
